{
	"name": "pl_adls_adb_connect",
	"properties": {
		"activities": [
			{
				"name": "Notebook1",
				"type": "DatabricksNotebook",
				"dependsOn": [],
				"policy": {
					"timeout": "0.12:00:00",
					"retry": 0,
					"retryIntervalInSeconds": 30,
					"secureOutput": false,
					"secureInput": false
				},
				"userProperties": [],
				"typeProperties": {
					"notebookPath": "/Users/ramprasad370b@gmail.com/ADF-ADB-Widget",
					"baseParameters": {
						"ADLS_Prefix": {
							"value": "@pipeline().globalParameters.ADLS_Prefix",
							"type": "Expression"
						}
					}
				},
				"linkedServiceName": {
					"referenceName": "ls_adb",
					"type": "LinkedServiceReference"
				}
			}
		],
		"folder": {
			"name": "ADB"
		},
		"annotations": []
	}
}